wqb/__init__.py
wqb/auto_auth_session.py
wqb/datetime_range.py
wqb/filter_range.py
wqb/wqb_session.py
wqb/wqb_urls.py
wqb_pre_release-0.1.29.dist-info/LICENSE
wqb_pre_release-0.1.29.dist-info/METADATA
wqb_pre_release-0.1.29.dist-info/WHEEL
wqb_pre_release-0.1.29.dist-info/top_level.txt
wqb_pre_release-0.1.29.dist-info/RECORD
