Metadata-Version: 2.2
Name: wqb-pre-release
Version: 0.1.29
Summary: A better machine lib.
Author-email: Rocky Haotian Du <qq2712479005@gmail.com>
License: MIT License
Classifier: Programming Language :: Python :: 3
Classifier: License :: OSI Approved :: MIT License
Classifier: Operating System :: OS Independent
Requires-Python: >=3.11
License-File: LICENSE
Requires-Dist: requests
